peaq_sdk/__init__.py
peaq_sdk/base.py
peaq_sdk/did.py
peaq_sdk/main.py
peaq_sdk/ptp.py
peaq_sdk/rbac.py
peaq_sdk/storage.py
peaq_sdk/transfer.py
peaq_sdk/types/__init__.py
peaq_sdk/types/base.py
peaq_sdk/types/common.py
peaq_sdk/types/did.py
peaq_sdk/types/main.py
peaq_sdk/types/rbac.py
peaq_sdk/types/storage.py
peaq_sdk/types/transfer.py
peaq_sdk/utils/__init__.py
peaq_sdk/utils/crypto.py
peaq_sdk/utils/peaq_proto.py
peaq_sdk/utils/utils.py
peaq_sdk-1.0.0.dist-info/METADATA
peaq_sdk-1.0.0.dist-info/WHEEL
peaq_sdk-1.0.0.dist-info/top_level.txt
peaq_sdk-1.0.0.dist-info/RECORD
