Metadata-Version: 2.4
Name: peaq-sdk
Version: 1.0.0
Summary: Peaq Network SDK for DID, Storage, RBAC operations, and blockchain interactions
Home-page: https://github.com/peaq-network/peaq-py/
Author: Peaq Network
Author-email: info@peaq.network
License: MIT
Classifier: Programming Language :: Python :: 3
Classifier: Programming Language :: Python :: 3.8
Classifier: Programming Language :: Python :: 3.9
Classifier: Programming Language :: Python :: 3.10
Classifier: Programming Language :: Python :: 3.11
Classifier: Programming Language :: Python :: 3.12
Classifier: Operating System :: OS Independent
Requires-Python: >=3.8
Requires-Dist: web3>=7.10.0
Requires-Dist: substrate-interface>=1.7.11
Requires-Dist: protobuf==5.28.2
Requires-Dist: varint==1.0.2
Requires-Dist: base58==2.1.1
